Metadata-Version: 2.1
Name: carpyncho
Version: 0.2
Summary: Python client for Carpyncho VVV dataset collection.
Home-page: https://carpyncho-py.readthedocs.io/
Author: J.B. Cabral
Author-email: jbc.develop@gmail.com
License: 3 Clause BSD
Keywords: astronomy,vvv,catalogs
Platform: UNKNOWN
Classifier: Development Status :: 4 - Beta
Classifier: Intended Audience :: Education
Classifier: Intended Audience :: Science/Research
Classifier: License :: OSI Approved :: BSD License
Classifier: Operating System :: OS Independent
Classifier: Programming Language :: Python
Classifier: Programming Language :: Python :: 3.7
Classifier: Programming Language :: Python :: 3.8
Classifier: Programming Language :: Python :: Implementation :: CPython
Classifier: Topic :: Scientific/Engineering
